star_shell/__init__.py
star_shell/backend.py
star_shell/command_executor.py
star_shell/command_safety.py
star_shell/context.py
star_shell/main.py
star_shell/mode_manager.py
star_shell/security.py
star_shell/session_manager.py
star_shell/utils.py
star_shell-0.5.4.dist-info/licenses/LICENSE
star_shell-0.5.4.dist-info/METADATA
star_shell-0.5.4.dist-info/WHEEL
star_shell-0.5.4.dist-info/entry_points.txt
star_shell-0.5.4.dist-info/top_level.txt
star_shell-0.5.4.dist-info/RECORD
