Metadata-Version: 2.4
Name: star-shell
Version: 0.5.4
Summary: AI-powered command line assistant that generates and executes shell commands
Author-email: Daniel Xu <imperialkoi9@gmail.com>
License: MIT
Project-URL: Homepage, https://github.com/ImperialKoi/Star-Shell
Project-URL: Repository, https://github.com/ImperialKoi/Star-Shell
Project-URL: Issues, https://github.com/ImperialKoi/Star-Shell/issues
Keywords: cli,ai,shell,command-line,assistant,automation,star-shell
Classifier: Development Status :: 4 - Beta
Classifier: Intended Audience :: Developers
Classifier: Intended Audience :: System Administrators
Classifier: License :: OSI Approved :: MIT License
Classifier: Operating System :: OS Independent
Classifier: Programming Language :: Python :: 3
Classifier: Programming Language :: Python :: 3.8
Classifier: Programming Language :: Python :: 3.9
Classifier: Programming Language :: Python :: 3.10
Classifier: Programming Language :: Python :: 3.11
Classifier: Programming Language :: Python :: 3.12
Classifier: Topic :: System :: Shells
Classifier: Topic :: Utilities
Classifier: Topic :: Software Development :: Libraries :: Python Modules
Requires-Python: >=3.8
License-File: LICENSE
Requires-Dist: google-generativeai>=0.3.0
Requires-Dist: openai
Requires-Dist: requests
Requires-Dist: typer
Requires-Dist: rich
Requires-Dist: pyperclip
Requires-Dist: cryptography
Dynamic: license-file
